python_recipy-0.1.14.dist-info/METADATA
python_recipy-0.1.14.dist-info/WHEEL
python_recipy-0.1.14.dist-info/entry_points.txt
python_recipy-0.1.14.dist-info/licenses/LICENSE
recipy/__init__.py
recipy/json_ld.py
recipy/latex.py
recipy/markdown.py
recipy/models.py
recipy/pdf.py
recipy/utils.py
python_recipy-0.1.14.dist-info/RECORD
