Metadata-Version: 2.1
Name: python-recipy
Version: 0.1.14
Summary: Extract recipes from web pages that use JSON-LD structured data and output Markdown, LaTeX, and PDF.
Author-Email: Kyle Kestell <kyle@kestell.org>
License: 0BSD
Requires-Python: >=3.8
Requires-Dist: markdown>=3.6
Requires-Dist: httpx>=0.27.0
Requires-Dist: beautifulsoup4>=4.12.3
Requires-Dist: nh3>=0.2.18
Requires-Dist: pydantic>=2.8.2
